Metadata-Version: 2.4
Name: basejump-chat2plot
Version: 0.0.11.post1
Summary: chat to visualization with LLM
Home-page: https://github.com/nyanp/chat2plot
Author: nyanp
Author-email: Noumi.Taiga@gmail.com
License: MIT
Keywords: llm visualization chart gpt
Classifier: License :: OSI Approved :: MIT License
Classifier: Programming Language :: Python :: 3.10
Classifier: Programming Language :: Python :: 3.11
License-File: LICENSE
Requires-Dist: altair>=4.2.0
Requires-Dist: commentjson==0.9.0
Requires-Dist: jsonschema
Requires-Dist: jsonref
Requires-Dist: openai>=0.27.0
Requires-Dist: pandas>=1.5.0
Requires-Dist: plotly>=5.0.0
Requires-Dist: streamlit-chat>=0.0.2.2
Requires-Dist: tabulate
Requires-Dist: vegafusion[embed]>=1.0
Requires-Dist: bs4
Dynamic: author
Dynamic: author-email
Dynamic: classifier
Dynamic: description
Dynamic: description-content-type
Dynamic: home-page
Dynamic: keywords
Dynamic: license
Dynamic: license-file
Dynamic: requires-dist
Dynamic: summary
